miwear/__init__.py
miwear/assert.py
miwear/gz.py
miwear/log.py
miwear/serialtool.py
miwear/targz.py
miwear/unzip.py
miwear/ymodem.py
miwear-0.0.12.dist-info/METADATA
miwear-0.0.12.dist-info/WHEEL
miwear-0.0.12.dist-info/entry_points.txt
miwear-0.0.12.dist-info/top_level.txt
miwear-0.0.12.dist-info/RECORD
