Metadata-Version: 2.4
Name: miwear
Version: 0.0.12
Summary: Python Miwear tools for extracting and handling archives/logs
Home-page: https://github.com/Junbo-Zheng/miwear
Author: Junbo Zheng
Author-email: Junbo Zheng <3273070@qq.com>
License: Apache-2.0
Project-URL: Homepage, https://github.com/Junbo-Zheng/miwear
Keywords: miwear,archive,log,extraction
Classifier: Programming Language :: Python :: 3
Classifier: License :: OSI Approved :: Apache Software License
Classifier: Operating System :: OS Independent
Requires-Python: >=3.7
Dynamic: author
Dynamic: home-page
Dynamic: requires-python
